setup.cfg
setup.py
PyWebmo/__init__.py
PyWebmo/webmo.py
PyWebmo.egg-info/PKG-INFO
PyWebmo.egg-info/SOURCES.txt
PyWebmo.egg-info/dependency_links.txt
PyWebmo.egg-info/requires.txt
PyWebmo.egg-info/top_level.txt