Metadata-Version: 1.1
Name: PyWebmo
Version: 0.1
Summary: Webmo client library for Python
Home-page: https://github.com/cidreixd/webmo-library-python
Author: Cidre Interaction Design Inc.
Author-email: info@cidre.tokyo
License: MIT
Download-URL: https://github.com/cidreixd/webmo-library-python/tarball/0.1
Keywords: webmo,websocket
Platform: UNKNOWN
